{
  "posts": [
    {
      "id": 1,
      "title": "json-server",
      "author": "typicode"
    }
  ],
  "comments": [
    {
      "id": 1,
      "body": "some comment",
      "postId": 1
    }
  ],
  "profile": {
    "name": "typicode"
  },
    "products": [
        {
        "id": 1,
        "title": "Product One",
        "price": 100
        },
        {
        "id": 2,
        "title": "Product Two",
        "price": 200
        },
        {
        "id": 3,
        "title": "Product Three",
        "price": 300
        }
    ],
    "news": [
        {
            "id": 1,
            "title": "News One",
            "description": "Description One",
            "category": "sports"
        },
        {
            "id": 2,
            "title": "News Two",
            "description": "Description Two",
            "category": "sports"
        },
        {
            "id": 3,
            "title": "News Three",
            "description": "Description Three",
            "category": "politics"
        }
    ],
    "dashboard":{
        "posts": 5,
        "likes": 100,
        "followers": 10,
        "following": 8
    },
    "events": [
      {
        "id": 1,
        "title": "Event 1",
        "description": "Description 1",
        "category": "sports",
        "date": "April 25"
      },
      {
        "id": 2,
        "title": "Event 2",
        "description": "Description 2",
        "category": "technology",
        "date": "May 25"
      },
      {
        "id": 3,
        "title": "Event 3",
        "description": "Description 3",
        "category": "food",
        "date": "October 25"
      },
      {
        "id": 4,
        "title": "Event 4",
        "description": "Description 4",
        "category": "food",
        "date": "April 25"
      },
      {
        "id": 5,
        "title": "Event 5",
        "description": "Description 5",
        "category": "sports",
        "date": "January 15"
      },
      {
        "id": 6,
        "title": "Event 6",
        "description": "Description 6",
        "category": "art",
        "date": "April 25"
      },
      {
        "id": 7,
        "title": "Event 7",
        "description": "Description 7",
        "category": "technology",
        "date": "June 25"
      },
      {
        "id": 8,
        "title": "Event 8",
        "description": "Description 8",
        "category": "sports",
        "date": "February 28"
      },
      {
        "id": 9,
        "title": "Event 9",
        "description": "Description 9",
        "category": "food",
        "date": "April 25"
      },
      {
        "id": 10,
        "title": "Event 10",
        "description": "Description 10",
        "category": "sports",
        "date": "August 5"
      }
    ]
}